json_verify/__init__.py
json_verify/json_verify.py
verify_json-1.0.2.data/data/README.rst
verify_json-1.0.2.dist-info/METADATA
verify_json-1.0.2.dist-info/WHEEL
verify_json-1.0.2.dist-info/top_level.txt
verify_json-1.0.2.dist-info/RECORD
