Metadata-Version: 2.1
Name: verify-json
Version: 1.0.2
Summary: A JSON contract tool that outputs build matches
Home-page: https://github.com/DaoSen-v/JsonDiff
Author: Ze Hua
Author-email: 1737985326@qq.com
License: MIT
Platform: UNKNOWN
